episema/__init__.py
episema/chant.py
episema/core.py
episema/gabc.py
episema/neumes.py
episema/signs.py
episema-0.1.0.dist-info/METADATA
episema-0.1.0.dist-info/WHEEL
episema-0.1.0.dist-info/RECORD
