Metadata-Version: 2.4
Name: episema
Version: 0.1.0
Summary: A Python library for rendering Gregorian Chant in square note notation
Keywords: gregorian,chant,square,note,solesmes,gabc
Author: Gabrieljoseg
Author-email: gabrielgomes9@gmail.com
Requires-Python: >=3.11
Classifier: Development Status :: 3 - Alpha
Classifier: Intended Audience :: Developers
Classifier: License :: OSI Approved :: MIT License
Classifier: Programming Language :: Python :: 3
Classifier: Programming Language :: Python :: 3.11
Classifier: Programming Language :: Python :: 3.12
